paper_siphon/__init__.py
paper_siphon/cleaning.py
paper_siphon/cli.py
paper_siphon-0.3.0.dist-info/METADATA
paper_siphon-0.3.0.dist-info/WHEEL
paper_siphon-0.3.0.dist-info/entry_points.txt
paper_siphon-0.3.0.dist-info/RECORD
