Metadata-Version: 2.4
Name: paper-siphon
Version: 0.3.0
Summary: Extract clean Markdown from academic PDFs - like drinking through a straw
Requires-Python: >=3.11
Requires-Dist: click>=8.1
Requires-Dist: docling>=2.0
Provides-Extra: mlx
Requires-Dist: mlx-vlm>=0.3; extra == 'mlx'
